aniScrape/__init__.py
aniscrape-1.0.0.dist-info/LICENSE
aniscrape-1.0.0.dist-info/METADATA
aniscrape-1.0.0.dist-info/WHEEL
aniscrape-1.0.0.dist-info/top_level.txt
aniscrape-1.0.0.dist-info/RECORD
