Metadata-Version: 2.1
Name: aniscrape
Version: 1.0.0
Summary: Scraper for aniSearch.de and .com
Home-page: https://github.com/TA40/aniScrape
Author: Tami 
Author-email: tammyshead@tuta.io
License: UNKNOWN
Platform: UNKNOWN
Classifier: Programming Language :: Python :: 3
Classifier: License :: OSI Approved :: MIT License
Classifier: Operating System :: OS Independent
